[{"position":"1Verstappen","driver":"Max Verstappen","nationality":"NED","car":"Red Bull Racing Honda RBPT","point":"195"},{"position":"2Perez","driver":"Sergio Perez","nationality":"MEX","car":"Red Bull Racing Honda RBPT","point":"126"},{"position":"3Alonso","driver":"Fernando Alonso","nationality":"ESP","car":"Aston Martin Aramco Mercedes","point":"117"},{"position":"4Hamilton","driver":"Lewis Hamilton","nationality":"GBR","car":"Mercedes","point":"102"},{"position":"5Sainz","driver":"Carlos Sainz","nationality":"ESP","car":"Ferrari","point":"68"},{"position":"6Russell","driver":"George Russell","nationality":"GBR","car":"Mercedes","point":"65"},{"position":"7Leclerc","driver":"Charles Leclerc","nationality":"MON","car":"Ferrari","point":"54"},{"position":"8Stroll","driver":"Lance Stroll","nationality":"CAN","car":"Aston Martin Aramco Mercedes","point":"37"},{"position":"9Ocon","driver":"Esteban Ocon","nationality":"FRA","car":"Alpine Renault","point":"29"},{"position":"10Gasly","driver":"Pierre Gasly","nationality":"FRA","car":"Alpine Renault","point":"15"},{"position":"11Norris","driver":"Lando Norris","nationality":"GBR","car":"McLaren Mercedes","point":"12"},{"position":"12Albon","driver":"Alexander Albon","nationality":"THA","car":"Williams Mercedes","point":"7"},{"position":"13Hulkenberg","driver":"Nico Hulkenberg","nationality":"GER","car":"Haas Ferrari","point":"6"},{"position":"14Piastri","driver":"Oscar Piastri","nationality":"AUS","car":"McLaren Mercedes","point":"5"},{"position":"15Bottas","driver":"Valtteri Bottas","nationality":"FIN","car":"Alfa Romeo Ferrari","point":"5"},{"position":"16Guanyu","driver":"Zhou Guanyu","nationality":"CHN","car":"Alfa Romeo Ferrari","point":"4"},{"position":"17Tsunoda","driver":"Yuki Tsunoda","nationality":"JPN","car":"AlphaTauri Honda RBPT","point":"2"},{"position":"18Magnussen","driver":"Kevin Magnussen","nationality":"DEN","car":"Haas Ferrari","point":"2"},{"position":"19De Vries","driver":"Nyck De Vries","nationality":"NED","car":"AlphaTauri Honda RBPT","point":"0"},{"position":"20Sargeant","driver":"Logan Sargeant","nationality":"USA","car":"Williams Mercedes","point":"0"}]